musiclib/__init__.py
musiclib/config.py
musiclib/interval.py
musiclib/intervalset.py
musiclib/note.py
musiclib/noteset.py
musiclib/pitch.py
musiclib/progression.py
musiclib/rhythm.py
musiclib/scale.py
musiclib/tempo.py
musiclib/midi/__init__.py
musiclib/midi/parse.py
musiclib/midi/pitchbend.py
musiclib/midi/player.py
musiclib/svg/__init__.py
musiclib/svg/card.py
musiclib/svg/header.py
musiclib/svg/nested.py
musiclib/svg/piano.py
musiclib/svg/pianoroll.py
musiclib/svg/reprsvg.py
musiclib/svg/isomorphic/__init__.py
musiclib/svg/isomorphic/base.py
musiclib/svg/isomorphic/hexagonal.py
musiclib/svg/isomorphic/piano.py
musiclib/svg/isomorphic/squared.py
musiclib/svg/isomorphic/text.py
musiclib/util/__init__.py
musiclib/util/cache.py
musiclib/util/etc.py
musiclib/voice_leading/__init__.py
musiclib/voice_leading/checks.py
musiclib/voice_leading/transition.py
musiclib-2.6.0.dist-info/METADATA
musiclib-2.6.0.dist-info/WHEEL
musiclib-2.6.0.dist-info/top_level.txt
musiclib-2.6.0.dist-info/RECORD
