Metadata-Version: 2.2
Name: musiclib
Version: 2.6.0
Summary: set of tools to work with scales, modes, modulations, chord progressions, voice leading, rhythm and more
Author-email: Alexander Rodionov <tandav@tandav.me>
Project-URL: source, https://github.com/tandav/musiclib
Project-URL: issues, https://gitlab.tandav.me/tandav/notes/-/issues/?label_name=musiclib
Project-URL: release notes, https://github.com/tandav/musiclib/releases
Requires-Python: >=3.11
Requires-Dist: colortool>=0.6.0
Requires-Dist: opseq>=0.1.2
Requires-Dist: mido>=1.3.0
Requires-Dist: svg.py
Requires-Dist: numpy
Provides-Extra: dev
Requires-Dist: bumpver==2023.1129; extra == "dev"
Requires-Dist: hypothesis==6.98.8; extra == "dev"
Requires-Dist: pre-commit==3.6.2; extra == "dev"
Requires-Dist: pytest==8.3.4; extra == "dev"
Requires-Dist: pytest-asyncio==0.23.5; extra == "dev"
Requires-Dist: pytest-cov==6.0.0; extra == "dev"
Provides-Extra: rtmidi
Requires-Dist: python-rtmidi; extra == "rtmidi"
